fuo_api/__init__.py
fuo_api/__main__.py
fuo_api/api.py
fuo_api-0.1.0.dist-info/METADATA
fuo_api-0.1.0.dist-info/WHEEL
fuo_api-0.1.0.dist-info/entry_points.txt
fuo_api-0.1.0.dist-info/top_level.txt
fuo_api-0.1.0.dist-info/RECORD
