Metadata-Version: 2.4
Name: fuo-api
Version: 0.1.0
Summary: FUOverflow image thread API server
Author-email: Your Name <you@example.com>
License: MIT
Requires-Python: >=3.8
Requires-Dist: fastapi
Requires-Dist: uvicorn[standard]
Requires-Dist: beautifulsoup4
Requires-Dist: requests
